{"assets/Ashram.png":["assets/Ashram.png"],"assets/Shirs.png":["assets/Shirs.png"],"assets/certifications.jpg":["assets/certifications.jpg"],"assets/close.png":["assets/close.png"],"assets/discord.png":["assets/discord.png"],"assets/drawer.png":["assets/drawer.png"],"assets/education.jpg":["assets/education.jpg"],"assets/github.png":["assets/github.png"],"assets/grid1.jpg":["assets/grid1.jpg"],"assets/grid2.jpg":["assets/grid2.jpg"],"assets/home.jpg":["assets/home.jpg"],"assets/insta.png":["assets/insta.png"],"assets/linkedin.png":["assets/linkedin.png"],"assets/mail.png":["assets/mail.png"],"assets/pinterest.png":["assets/pinterest.png"],"assets/skills.jpg":["assets/skills.jpg"],"assets/stJosephs.png":["assets/stJosephs.png"],"packages/cupertino_icons/assets/CupertinoIcons.ttf":["packages/cupertino_icons/assets/CupertinoIcons.ttf"]}